pyunwrap.cpython-38-darwin.so
pyunwrap-0.0.4.dist-info/RECORD
pyunwrap-0.0.4.dist-info/WHEEL
pyunwrap-0.0.4.dist-info/top_level.txt
pyunwrap-0.0.4.dist-info/METADATA
