Metadata-Version: 2.1
Name: pyunwrap
Version: 0.0.4
Provides-Extra: dev
Requires-Dist: pybind11 ; extra == 'dev'
